uppercase/__init__.py
uppercase/__main__.py
102218023_TEXTCONVERTOR-1.0.0.dist-info/METADATA
102218023_TEXTCONVERTOR-1.0.0.dist-info/WHEEL
102218023_TEXTCONVERTOR-1.0.0.dist-info/entry_points.txt
102218023_TEXTCONVERTOR-1.0.0.dist-info/top_level.txt
102218023_TEXTCONVERTOR-1.0.0.dist-info/RECORD
