Metadata-Version: 2.1
Name: 102218023_TEXTCONVERTOR
Version: 1.0.0
Summary: This package provides a simple tool to convert the contents of a file to uppercase.
Home-page: 
Author: JASHANDEEP SINGH
Author-email: jashandeepgarry2003@gmail.com
License: MIT
Classifier: License :: OSI Approved :: MIT License
